{"map":"any","isGlobalForChampions":false,"blocks":[{"items":[{"count":1,"id":"1039"},{"count":1,"id":"2003"},{"count":1,"id":"2003"},{"count":1,"id":"2003"}],"type":"Most frequent Starters (50.44% win - 2684 games)"},{"items":[{"count":1,"id":"1041"},{"count":1,"id":"2031"}],"type":"Highest Winrate Starters (54.75% win - 221 games)"},{"items":[{"count":1,"id":"1402"},{"count":1,"id":"3158"},{"count":1,"id":"3157"},{"count":1,"id":"3100"},{"count":1,"id":"3089"},{"count":1,"id":"3135"}],"type":"Most frequent Build (49.63% win - 209 games)"},{"items":[{"count":1,"id":"1402"},{"count":1,"id":"3158"},{"count":1,"id":"3115"},{"count":1,"id":"3116"},{"count":1,"id":"3157"},{"count":1,"id":"3135"}],"type":"Highest Winrate Build (51.86% win - 159 games)"},{"items":[{"count":1,"id":"3340"},{"count":1,"id":"3341"},{"count":1,"id":"3364"},{"count":1,"id":"3363"}],"type":"WQQEQR > QWQWRW > WEEREE (49.6% win - 1661 games)"},{"items":[{"count":1,"id":"2003"},{"count":1,"id":"2044"},{"count":1,"id":"2043"},{"count":1,"id":"2041"},{"count":1,"id":"2138"},{"count":1,"id":"2137"},{"count":1,"id":"2139"},{"count":1,"id":"2140"}],"type":"WQWQER > QQQWRW > WEEREE (55.88% win - 204 games)"}],"associatedChampions":[],"title":"Jungle","priority":false,"mode":"any","isGlobalForMaps":true,"associatedMaps":[],"type":"custom","softrank":1,"champion":"Diana"}